{
    "graph": {
        "Vaults": {
            "ResourceInfo": {
                "Id": "azurerm_key_vault.foo",
                "HasId": true,
                "Name": "foo",
                "HasName": true,
                "Csp": "",
                "HasCsp": false,
                "ResourceType": "Microsoft.KeyVault/vaults",
                "HasResourceType": true,
                "Tags": {},
                "BlueprintId": "",
                "HasBlueprintId": false,
                "Context": null
            },
            "Location": "azurerm_resource_group.foo.location",
            "Name": "foo-vault_key",
            "AccessPolicies": [],
            "CreateMode": "",
            "EnabledForDeployment": true,
            "EnabledForDiskEncryption": true,
            "EnabledForTemplateDeployment": true,
            "EnablePurgeProtection": false,
            "EnableRbacAuthorization": false,
            "EnableSoftDelete": false,
            "NetworkAcls": {
                "Bypass": "",
                "DefaultAction": "",
                "IpRules": [],
                "VirtualNetworkRules": []
            },
            "ProvisioningState": "",
            "PublicNetworkAccess": "",
            "Sku": {
                "Family": "",
                "Name": "premium"
            },
            "SoftDeleteRetentionInDays": 7,
            "TenantId": "data.azurerm_client_config.current.tenant_id",
            "VaultUri": "",
            "Tags": {},
            "VaultsPrivateEndpointConnections": []
        },
        "VaultsAccessPolicies": [],
        "VaultsKeys": [],
        "VaultsSecrets": []
    },
    "blueprint": {
        "BlueprintId": "bp.component.638000760660764840",
        "ParentBlueprintId": "Oak9.KMS.KeyManagementService.CSPManaged",
        "BlueprintName": "CSP Managed Key Management Service",
        "Status": "",
        "HasStatus": false,
        "Description": "A Cloud Service Provider Managed Key Management Service. This component represents key management services provided by CSPs such as AWS, MS Azure or GCP where the CSP manages the cryptographic keys on behalf of the Customer Organization.",
        "Type": "Component",
        "Revision": "",
        "Version": "",
        "Author": "oak9",
        "ComplianceObjectives": [],
        "LastUpdatedOn": null,
        "ComponentInfo": null,
        "BlueprintReference": null,
        "Requirements": [
            {
                "Id": "Oak9.CR.AA.1",
                "HasId": true,
                "Context": null,
                "Description": "Validate that all security-relevant events for the component are logged and ensure the integrity of collected logs",
                "HasDescription": true,
                "Version": "",
                "HasVersion": false,
                "Type": "",
                "HasType": false,
                "Category": "Audit and Accountability",
                "HasCategory": true,
                "SubCategory": "",
                "HasSubCategory": false,
                "Component": "",
                "HasComponent": false,
                "Tags": "",
                "HasTags": false,
                "Guidance": "",
                "HasGuidance": false,
                "HiTrustMapping": "",
                "HasHiTrustMapping": false,
                "HiTrust94Mapping": "",
                "HasHiTrust94Mapping": false,
                "NistMapping": "",
                "HasNistMapping": false,
                "IndustryFrameworks": [],
                "HlRs": "",
                "HasHlRs": false
            },
            {
                "Id": "Oak9.CR.AE.1",
                "HasId": true,
                "Context": null,
                "Description": "Ensure the integrity and authenticity of the applicaiton session, and enforce minimum necessary access.",
                "HasDescription": true,
                "Version": "",
                "HasVersion": false,
                "Type": "",
                "HasType": false,
                "Category": "Access Enforcement",
                "HasCategory": true,
                "SubCategory": "",
                "HasSubCategory": false,
                "Component": "",
                "HasComponent": false,
                "Tags": "",
                "HasTags": false,
                "Guidance": "",
                "HasGuidance": false,
                "HiTrustMapping": "",
                "HasHiTrustMapping": false,
                "HiTrust94Mapping": "",
                "HasHiTrust94Mapping": false,
                "NistMapping": "",
                "HasNistMapping": false,
                "IndustryFrameworks": [],
                "HlRs": "",
                "HasHlRs": false
            },
            {
                "Id": "Oak9.CR.AE.2",
                "HasId": true,
                "Context": null,
                "Description": "Enforce the access control policy and ensure minimum necessary access",
                "HasDescription": true,
                "Version": "",
                "HasVersion": false,
                "Type": "",
                "HasType": false,
                "Category": "Access Enforcement",
                "HasCategory": true,
                "SubCategory": "",
                "HasSubCategory": false,
                "Component": "",
                "HasComponent": false,
                "Tags": "",
                "HasTags": false,
                "Guidance": "",
                "HasGuidance": false,
                "HiTrustMapping": "",
                "HasHiTrustMapping": false,
                "HiTrust94Mapping": "",
                "HasHiTrust94Mapping": false,
                "NistMapping": "",
                "HasNistMapping": false,
                "IndustryFrameworks": [],
                "HlRs": "",
                "HasHlRs": false
            },
            {
                "Id": "Oak9.CR.AE.3",
                "HasId": true,
                "Context": null,
                "Description": "Ensure that all privileged access is managed through approved processes, in accordance with standards and best practices",
                "HasDescription": true,
                "Version": "",
                "HasVersion": false,
                "Type": "",
                "HasType": false,
                "Category": "Access Enforcement",
                "HasCategory": true,
                "SubCategory": "",
                "HasSubCategory": false,
                "Component": "",
                "HasComponent": false,
                "Tags": "",
                "HasTags": false,
                "Guidance": "",
                "HasGuidance": false,
                "HiTrustMapping": "",
                "HasHiTrustMapping": false,
                "HiTrust94Mapping": "",
                "HasHiTrust94Mapping": false,
                "NistMapping": "",
                "HasNistMapping": false,
                "IndustryFrameworks": [],
                "HlRs": "",
                "HasHlRs": false
            },
            {
                "Id": "Oak9.CR.AI.1",
                "HasId": true,
                "Context": null,
                "Description": "Maintain an accurate asset inventory of all information systems, components, and data",
                "HasDescription": true,
                "Version": "",
                "HasVersion": false,
                "Type": "",
                "HasType": false,
                "Category": "Asset Inventory",
                "HasCategory": true,
                "SubCategory": "",
                "HasSubCategory": false,
                "Component": "",
                "HasComponent": false,
                "Tags": "",
                "HasTags": false,
                "Guidance": "",
                "HasGuidance": false,
                "HiTrustMapping": "",
                "HasHiTrustMapping": false,
                "HiTrust94Mapping": "",
                "HasHiTrust94Mapping": false,
                "NistMapping": "",
                "HasNistMapping": false,
                "IndustryFrameworks": [],
                "HlRs": "",
                "HasHlRs": false
            },
            {
                "Id": "Oak9.CR.BR.1",
                "HasId": true,
                "Context": null,
                "Description": "Design a highly available architecture that ensures the availability of essential business functions in accordance with organizational policies and standards",
                "HasDescription": true,
                "Version": "",
                "HasVersion": false,
                "Type": "",
                "HasType": false,
                "Category": "Business Resilience",
                "HasCategory": true,
                "SubCategory": "",
                "HasSubCategory": false,
                "Component": "",
                "HasComponent": false,
                "Tags": "",
                "HasTags": false,
                "Guidance": "",
                "HasGuidance": false,
                "HiTrustMapping": "",
                "HasHiTrustMapping": false,
                "HiTrust94Mapping": "",
                "HasHiTrust94Mapping": false,
                "NistMapping": "",
                "HasNistMapping": false,
                "IndustryFrameworks": [],
                "HlRs": "",
                "HasHlRs": false
            },
            {
                "Id": "Oak9.CR.CM.1",
                "HasId": true,
                "Context": null,
                "Description": "Harden the configuration of the component to minimize the attack surface",
                "HasDescription": true,
                "Version": "",
                "HasVersion": false,
                "Type": "",
                "HasType": false,
                "Category": "Configuration Management",
                "HasCategory": true,
                "SubCategory": "",
                "HasSubCategory": false,
                "Component": "",
                "HasComponent": false,
                "Tags": "",
                "HasTags": false,
                "Guidance": "",
                "HasGuidance": false,
                "HiTrustMapping": "",
                "HasHiTrustMapping": false,
                "HiTrust94Mapping": "",
                "HasHiTrust94Mapping": false,
                "NistMapping": "",
                "HasNistMapping": false,
                "IndustryFrameworks": [],
                "HlRs": "",
                "HasHlRs": false
            },
            {
                "Id": "Oak9.CR.DAR.1",
                "HasId": true,
                "Context": null,
                "Description": "Protect the confidentiality of data using built-in capabilities of the platform",
                "HasDescription": true,
                "Version": "",
                "HasVersion": false,
                "Type": "",
                "HasType": false,
                "Category": "Data-at-Rest Protection",
                "HasCategory": true,
                "SubCategory": "",
                "HasSubCategory": false,
                "Component": "",
                "HasComponent": false,
                "Tags": "",
                "HasTags": false,
                "Guidance": "",
                "HasGuidance": false,
                "HiTrustMapping": "",
                "HasHiTrustMapping": false,
                "HiTrust94Mapping": "",
                "HasHiTrust94Mapping": false,
                "NistMapping": "",
                "HasNistMapping": false,
                "IndustryFrameworks": [],
                "HlRs": "",
                "HasHlRs": false
            },
            {
                "Id": "Oak9.CR.DAR.4",
                "HasId": true,
                "Context": null,
                "Description": "Ensure data is securely removed when no longer needed",
                "HasDescription": true,
                "Version": "",
                "HasVersion": false,
                "Type": "",
                "HasType": false,
                "Category": "Data-at-Rest Protection",
                "HasCategory": true,
                "SubCategory": "",
                "HasSubCategory": false,
                "Component": "",
                "HasComponent": false,
                "Tags": "",
                "HasTags": false,
                "Guidance": "",
                "HasGuidance": false,
                "HiTrustMapping": "",
                "HasHiTrustMapping": false,
                "HiTrust94Mapping": "",
                "HasHiTrust94Mapping": false,
                "NistMapping": "",
                "HasNistMapping": false,
                "IndustryFrameworks": [],
                "HlRs": "",
                "HasHlRs": false
            },
            {
                "Id": "Oak9.CR.DIT.1",
                "HasId": true,
                "Context": null,
                "Description": "Protect confidentiality and integrity of data-in-transit using industry standard Transport Layer Security (TLS) protocols",
                "HasDescription": true,
                "Version": "",
                "HasVersion": false,
                "Type": "",
                "HasType": false,
                "Category": "Data-in-Transit Protection",
                "HasCategory": true,
                "SubCategory": "",
                "HasSubCategory": false,
                "Component": "",
                "HasComponent": false,
                "Tags": "",
                "HasTags": false,
                "Guidance": "",
                "HasGuidance": false,
                "HiTrustMapping": "",
                "HasHiTrustMapping": false,
                "HiTrust94Mapping": "",
                "HasHiTrust94Mapping": false,
                "NistMapping": "",
                "HasNistMapping": false,
                "IndustryFrameworks": [],
                "HlRs": "",
                "HasHlRs": false
            },
            {
                "Id": "Oak9.CR.DIU.1",
                "HasId": true,
                "Context": null,
                "Description": "Securely wipe sensitive data in memory once that data is no longer needed by the process",
                "HasDescription": true,
                "Version": "",
                "HasVersion": false,
                "Type": "",
                "HasType": false,
                "Category": "Data-in-Use Protection",
                "HasCategory": true,
                "SubCategory": "",
                "HasSubCategory": false,
                "Component": "",
                "HasComponent": false,
                "Tags": "",
                "HasTags": false,
                "Guidance": "",
                "HasGuidance": false,
                "HiTrustMapping": "",
                "HasHiTrustMapping": false,
                "HiTrust94Mapping": "",
                "HasHiTrust94Mapping": false,
                "NistMapping": "",
                "HasNistMapping": false,
                "IndustryFrameworks": [],
                "HlRs": "",
                "HasHlRs": false
            },
            {
                "Id": "Oak9.CR.DM.1",
                "HasId": true,
                "Context": null,
                "Description": "Reduce the attack surface by minimizing the collection and aggregation of data",
                "HasDescription": true,
                "Version": "",
                "HasVersion": false,
                "Type": "",
                "HasType": false,
                "Category": "Data Minimization",
                "HasCategory": true,
                "SubCategory": "",
                "HasSubCategory": false,
                "Component": "",
                "HasComponent": false,
                "Tags": "",
                "HasTags": false,
                "Guidance": "",
                "HasGuidance": false,
                "HiTrustMapping": "",
                "HasHiTrustMapping": false,
                "HiTrust94Mapping": "",
                "HasHiTrust94Mapping": false,
                "NistMapping": "",
                "HasNistMapping": false,
                "IndustryFrameworks": [],
                "HlRs": "",
                "HasHlRs": false
            },
            {
                "Id": "Oak9.CR.DM.3",
                "HasId": true,
                "Context": null,
                "Description": "Ensure a proper data retention plan is in place to meet business and compliance needs.  ",
                "HasDescription": true,
                "Version": "",
                "HasVersion": false,
                "Type": "",
                "HasType": false,
                "Category": "Data Minimization",
                "HasCategory": true,
                "SubCategory": "",
                "HasSubCategory": false,
                "Component": "",
                "HasComponent": false,
                "Tags": "",
                "HasTags": false,
                "Guidance": "",
                "HasGuidance": false,
                "HiTrustMapping": "",
                "HasHiTrustMapping": false,
                "HiTrust94Mapping": "",
                "HasHiTrust94Mapping": false,
                "NistMapping": "",
                "HasNistMapping": false,
                "IndustryFrameworks": [],
                "HlRs": "",
                "HasHlRs": false
            },
            {
                "Id": "Oak9.CR.DMP.1",
                "HasId": true,
                "Context": null,
                "Description": "Detect and protect against data mining attacks on data stores",
                "HasDescription": true,
                "Version": "",
                "HasVersion": false,
                "Type": "",
                "HasType": false,
                "Category": "Data Mining Protection",
                "HasCategory": true,
                "SubCategory": "",
                "HasSubCategory": false,
                "Component": "",
                "HasComponent": false,
                "Tags": "",
                "HasTags": false,
                "Guidance": "",
                "HasGuidance": false,
                "HiTrustMapping": "",
                "HasHiTrustMapping": false,
                "HiTrust94Mapping": "",
                "HasHiTrust94Mapping": false,
                "NistMapping": "",
                "HasNistMapping": false,
                "IndustryFrameworks": [],
                "HlRs": "",
                "HasHlRs": false
            },
            {
                "Id": "Oak9.CR.DOS.1",
                "HasId": true,
                "Context": null,
                "Description": "Protect against denial-of-service attacks",
                "HasDescription": true,
                "Version": "",
                "HasVersion": false,
                "Type": "",
                "HasType": false,
                "Category": "Denial of Service Protection",
                "HasCategory": true,
                "SubCategory": "",
                "HasSubCategory": false,
                "Component": "",
                "HasComponent": false,
                "Tags": "",
                "HasTags": false,
                "Guidance": "",
                "HasGuidance": false,
                "HiTrustMapping": "",
                "HasHiTrustMapping": false,
                "HiTrust94Mapping": "",
                "HasHiTrust94Mapping": false,
                "NistMapping": "",
                "HasNistMapping": false,
                "IndustryFrameworks": [],
                "HlRs": "",
                "HasHlRs": false
            },
            {
                "Id": "Oak9.CR.IFE.1",
                "HasId": true,
                "Context": null,
                "Description": "Utilize firewalls to control the flow of information",
                "HasDescription": true,
                "Version": "",
                "HasVersion": false,
                "Type": "",
                "HasType": false,
                "Category": "Information Flow Enforcement",
                "HasCategory": true,
                "SubCategory": "",
                "HasSubCategory": false,
                "Component": "",
                "HasComponent": false,
                "Tags": "",
                "HasTags": false,
                "Guidance": "",
                "HasGuidance": false,
                "HiTrustMapping": "",
                "HasHiTrustMapping": false,
                "HiTrust94Mapping": "",
                "HasHiTrust94Mapping": false,
                "NistMapping": "",
                "HasNistMapping": false,
                "IndustryFrameworks": [],
                "HlRs": "",
                "HasHlRs": false
            },
            {
                "Id": "Oak9.CR.FT.1",
                "HasId": true,
                "Context": null,
                "Description": "Design applications to be fault-tolerant",
                "HasDescription": true,
                "Version": "",
                "HasVersion": false,
                "Type": "",
                "HasType": false,
                "Category": "Fault Tolerance",
                "HasCategory": true,
                "SubCategory": "",
                "HasSubCategory": false,
                "Component": "",
                "HasComponent": false,
                "Tags": "",
                "HasTags": false,
                "Guidance": "",
                "HasGuidance": false,
                "HiTrustMapping": "",
                "HasHiTrustMapping": false,
                "HiTrust94Mapping": "",
                "HasHiTrust94Mapping": false,
                "NistMapping": "",
                "HasNistMapping": false,
                "IndustryFrameworks": [],
                "HlRs": "",
                "HasHlRs": false
            },
            {
                "Id": "Oak9.CR.IA.1",
                "HasId": true,
                "Context": null,
                "Description": "Uniquely identify and authenticate person and non-person users using protocols that ensure the integrity of the authentication process",
                "HasDescription": true,
                "Version": "",
                "HasVersion": false,
                "Type": "",
                "HasType": false,
                "Category": "Identification and Authentication",
                "HasCategory": true,
                "SubCategory": "",
                "HasSubCategory": false,
                "Component": "",
                "HasComponent": false,
                "Tags": "",
                "HasTags": false,
                "Guidance": "",
                "HasGuidance": false,
                "HiTrustMapping": "",
                "HasHiTrustMapping": false,
                "HiTrust94Mapping": "",
                "HasHiTrust94Mapping": false,
                "NistMapping": "",
                "HasNistMapping": false,
                "IndustryFrameworks": [],
                "HlRs": "",
                "HasHlRs": false
            },
            {
                "Id": "Oak9.CR.IFE.5",
                "HasId": true,
                "Context": null,
                "Description": "Use automation to dynamically isolate and segregate applications or application components in reaction to changing business and security requirements",
                "HasDescription": true,
                "Version": "",
                "HasVersion": false,
                "Type": "",
                "HasType": false,
                "Category": "Information Flow Enforcement",
                "HasCategory": true,
                "SubCategory": "",
                "HasSubCategory": false,
                "Component": "",
                "HasComponent": false,
                "Tags": "",
                "HasTags": false,
                "Guidance": "",
                "HasGuidance": false,
                "HiTrustMapping": "",
                "HasHiTrustMapping": false,
                "HiTrust94Mapping": "",
                "HasHiTrust94Mapping": false,
                "NistMapping": "",
                "HasNistMapping": false,
                "IndustryFrameworks": [],
                "HlRs": "",
                "HasHlRs": false
            },
            {
                "Id": "Oak9.CR.IFE.3",
                "HasId": true,
                "Context": null,
                "Description": "Prevent discovery of application or system information (e.g. IP addresses) and limit feedback to minimum necessary, such that attackers are required to have prior knowledge, or engage in prolonged reconnaissance, to successfully target the application",
                "HasDescription": true,
                "Version": "",
                "HasVersion": false,
                "Type": "",
                "HasType": false,
                "Category": "Information Flow Enforcement",
                "HasCategory": true,
                "SubCategory": "",
                "HasSubCategory": false,
                "Component": "",
                "HasComponent": false,
                "Tags": "",
                "HasTags": false,
                "Guidance": "",
                "HasGuidance": false,
                "HiTrustMapping": "",
                "HasHiTrustMapping": false,
                "HiTrust94Mapping": "",
                "HasHiTrust94Mapping": false,
                "NistMapping": "",
                "HasNistMapping": false,
                "IndustryFrameworks": [],
                "HlRs": "",
                "HasHlRs": false
            },
            {
                "Id": "Oak9.CR.IFE.4",
                "HasId": true,
                "Context": null,
                "Description": "Isolate and segregate information systems and components from other systems and components based on criteria that, at minimum, includes functionality required, business impact of a breach, threat exposure and the associated business risk profile of the information system and component",
                "HasDescription": true,
                "Version": "",
                "HasVersion": false,
                "Type": "",
                "HasType": false,
                "Category": "Information Flow Enforcement",
                "HasCategory": true,
                "SubCategory": "",
                "HasSubCategory": false,
                "Component": "",
                "HasComponent": false,
                "Tags": "",
                "HasTags": false,
                "Guidance": "",
                "HasGuidance": false,
                "HiTrustMapping": "",
                "HasHiTrustMapping": false,
                "HiTrust94Mapping": "",
                "HasHiTrust94Mapping": false,
                "NistMapping": "",
                "HasNistMapping": false,
                "IndustryFrameworks": [],
                "HlRs": "",
                "HasHlRs": false
            },
            {
                "Id": "Oak9.CR.ILM.1",
                "HasId": true,
                "Context": null,
                "Description": "Integrate with approved identity lifecycle management capabilities that address the entire lifecycle of the identity and related accounts to ensure that the trust placed in a given identity is commensurate with the risks of that identity being forged, spoofed or compromised",
                "HasDescription": true,
                "Version": "",
                "HasVersion": false,
                "Type": "",
                "HasType": false,
                "Category": "Identity and Account Lifecycle Management",
                "HasCategory": true,
                "SubCategory": "",
                "HasSubCategory": false,
                "Component": "",
                "HasComponent": false,
                "Tags": "",
                "HasTags": false,
                "Guidance": "",
                "HasGuidance": false,
                "HiTrustMapping": "",
                "HasHiTrustMapping": false,
                "HiTrust94Mapping": "",
                "HasHiTrust94Mapping": false,
                "NistMapping": "",
                "HasNistMapping": false,
                "IndustryFrameworks": [],
                "HlRs": "",
                "HasHlRs": false
            },
            {
                "Id": "Oak9.CR.ILM.2",
                "HasId": true,
                "Context": null,
                "Description": "Ensure role-based access control, by organizing access and privileges into roles and managing the lifecycle of these roles in accordance with existing standards & best practices",
                "HasDescription": true,
                "Version": "",
                "HasVersion": false,
                "Type": "",
                "HasType": false,
                "Category": "Identity and Account Lifecycle Management",
                "HasCategory": true,
                "SubCategory": "",
                "HasSubCategory": false,
                "Component": "",
                "HasComponent": false,
                "Tags": "",
                "HasTags": false,
                "Guidance": "",
                "HasGuidance": false,
                "HiTrustMapping": "",
                "HasHiTrustMapping": false,
                "HiTrust94Mapping": "",
                "HasHiTrust94Mapping": false,
                "NistMapping": "",
                "HasNistMapping": false,
                "IndustryFrameworks": [],
                "HlRs": "",
                "HasHlRs": false
            },
            {
                "Id": "Oak9.CR.ILM.3",
                "HasId": true,
                "Context": null,
                "Description": "Enforce separation of duties to reduce the risk of malevolent activity without collusion, commensurate with the business impact of the abuse of an individual's authorized privileges",
                "HasDescription": true,
                "Version": "",
                "HasVersion": false,
                "Type": "",
                "HasType": false,
                "Category": "Identity and Account Lifecycle Management",
                "HasCategory": true,
                "SubCategory": "",
                "HasSubCategory": false,
                "Component": "",
                "HasComponent": false,
                "Tags": "",
                "HasTags": false,
                "Guidance": "",
                "HasGuidance": false,
                "HiTrustMapping": "",
                "HasHiTrustMapping": false,
                "HiTrust94Mapping": "",
                "HasHiTrust94Mapping": false,
                "NistMapping": "",
                "HasNistMapping": false,
                "IndustryFrameworks": [],
                "HlRs": "",
                "HasHlRs": false
            },
            {
                "Id": "Oak9.CR.KM.1",
                "HasId": true,
                "Context": null,
                "Description": "Protect cryptographic keys and manage their lifecycle in a manner commensurate with the business impact of the loss of the key",
                "HasDescription": true,
                "Version": "",
                "HasVersion": false,
                "Type": "",
                "HasType": false,
                "Category": "Key Management",
                "HasCategory": true,
                "SubCategory": "",
                "HasSubCategory": false,
                "Component": "",
                "HasComponent": false,
                "Tags": "",
                "HasTags": false,
                "Guidance": "",
                "HasGuidance": false,
                "HiTrustMapping": "",
                "HasHiTrustMapping": false,
                "HiTrust94Mapping": "",
                "HasHiTrust94Mapping": false,
                "NistMapping": "",
                "HasNistMapping": false,
                "IndustryFrameworks": [],
                "HlRs": "",
                "HasHlRs": false
            },
            {
                "Id": "Oak9.CR.SS.3",
                "HasId": true,
                "Context": null,
                "Description": "Validate that the latest security patches to all systems and applications are applied",
                "HasDescription": true,
                "Version": "",
                "HasVersion": false,
                "Type": "",
                "HasType": false,
                "Category": "System Security",
                "HasCategory": true,
                "SubCategory": "",
                "HasSubCategory": false,
                "Component": "",
                "HasComponent": false,
                "Tags": "",
                "HasTags": false,
                "Guidance": "",
                "HasGuidance": false,
                "HiTrustMapping": "",
                "HasHiTrustMapping": false,
                "HiTrust94Mapping": "",
                "HasHiTrust94Mapping": false,
                "NistMapping": "",
                "HasNistMapping": false,
                "IndustryFrameworks": [],
                "HlRs": "",
                "HasHlRs": false
            },
            {
                "Id": "Oak9.CR.SS.5",
                "HasId": true,
                "Context": null,
                "Description": "Release shared system resources (e.g., registers, main memory, secondary storage) back to the information system, protect them from disclosure to other systems/applications/Users, and prevent Users from intentionally or unintentionally accessing information remnants",
                "HasDescription": true,
                "Version": "",
                "HasVersion": false,
                "Type": "",
                "HasType": false,
                "Category": "System Security",
                "HasCategory": true,
                "SubCategory": "",
                "HasSubCategory": false,
                "Component": "",
                "HasComponent": false,
                "Tags": "",
                "HasTags": false,
                "Guidance": "",
                "HasGuidance": false,
                "HiTrustMapping": "",
                "HasHiTrustMapping": false,
                "HiTrust94Mapping": "",
                "HasHiTrust94Mapping": false,
                "NistMapping": "",
                "HasNistMapping": false,
                "IndustryFrameworks": [],
                "HlRs": "",
                "HasHlRs": false
            },
            {
                "Id": "Oak9.CR.SS.4",
                "HasId": true,
                "Context": null,
                "Description": "Validate configuration of integrity monitoring capabilities",
                "HasDescription": true,
                "Version": "",
                "HasVersion": false,
                "Type": "",
                "HasType": false,
                "Category": "System Security",
                "HasCategory": true,
                "SubCategory": "",
                "HasSubCategory": false,
                "Component": "",
                "HasComponent": false,
                "Tags": "",
                "HasTags": false,
                "Guidance": "",
                "HasGuidance": false,
                "HiTrustMapping": "",
                "HasHiTrustMapping": false,
                "HiTrust94Mapping": "",
                "HasHiTrust94Mapping": false,
                "NistMapping": "",
                "HasNistMapping": false,
                "IndustryFrameworks": [],
                "HlRs": "",
                "HasHlRs": false
            },
            {
                "Id": "Oak9.CR.TC.1",
                "HasId": true,
                "Context": null,
                "Description": "Provide a trusted computing environment for the application",
                "HasDescription": true,
                "Version": "",
                "HasVersion": false,
                "Type": "",
                "HasType": false,
                "Category": "Trusted Computing",
                "HasCategory": true,
                "SubCategory": "",
                "HasSubCategory": false,
                "Component": "",
                "HasComponent": false,
                "Tags": "",
                "HasTags": false,
                "Guidance": "",
                "HasGuidance": false,
                "HiTrustMapping": "",
                "HasHiTrustMapping": false,
                "HiTrust94Mapping": "",
                "HasHiTrust94Mapping": false,
                "NistMapping": "",
                "HasNistMapping": false,
                "IndustryFrameworks": [],
                "HlRs": "",
                "HasHlRs": false
            },
            {
                "Id": "Oak9.CR.VM.1",
                "HasId": true,
                "Context": null,
                "Description": "Remediate all known vulnerabilities in Customer Organization systems and applications",
                "HasDescription": true,
                "Version": "",
                "HasVersion": false,
                "Type": "",
                "HasType": false,
                "Category": "Vulnerability Management",
                "HasCategory": true,
                "SubCategory": "",
                "HasSubCategory": false,
                "Component": "",
                "HasComponent": false,
                "Tags": "",
                "HasTags": false,
                "Guidance": "",
                "HasGuidance": false,
                "HiTrustMapping": "",
                "HasHiTrustMapping": false,
                "HiTrust94Mapping": "",
                "HasHiTrust94Mapping": false,
                "NistMapping": "",
                "HasNistMapping": false,
                "IndustryFrameworks": [],
                "HlRs": "",
                "HasHlRs": false
            },
            {
                "Id": "Oak9.CR.SS.2",
                "HasId": true,
                "Context": null,
                "Description": "Ensure the integrity of name/address resolution information and only retrieve this information from trusted authoritative sources",
                "HasDescription": true,
                "Version": "",
                "HasVersion": false,
                "Type": "",
                "HasType": false,
                "Category": "System Security",
                "HasCategory": true,
                "SubCategory": "",
                "HasSubCategory": false,
                "Component": "",
                "HasComponent": false,
                "Tags": "",
                "HasTags": false,
                "Guidance": "",
                "HasGuidance": false,
                "HiTrustMapping": "",
                "HasHiTrustMapping": false,
                "HiTrust94Mapping": "",
                "HasHiTrust94Mapping": false,
                "NistMapping": "",
                "HasNistMapping": false,
                "IndustryFrameworks": [],
                "HlRs": "",
                "HasHlRs": false
            }
        ],
        "IsDeleted": false,
        "ReferenceProjectId": "",
        "HasReferenceProjectId": false,
        "Context": null,
        "Blueprints": []
    },
    "metaInfo": {
        "Caller": "Cli",
        "RequestId": "b27bfd37-620a-4117-a0cc-0dc0a98aed9b",
        "ResourceType": "Microsoft.KeyVault",
        "BlueprintId": "bp.component.638000760660764840",
        "ResourceName": "foo",
        "ResourceId": "Microsoft.KeyVault-05bbaa15-6e22-9b5a-d336-7fd6c1110032"
    }
}